pyfzf/__init__.py
pyfzf/pyfzf.py
pyfzf-0.3.0.dist-info/LICENSE
pyfzf-0.3.0.dist-info/METADATA
pyfzf-0.3.0.dist-info/WHEEL
pyfzf-0.3.0.dist-info/top_level.txt
pyfzf-0.3.0.dist-info/RECORD
