Metadata-Version: 2.1
Name: pyfzf
Version: 0.3.0
Summary: Python wrapper for junegunn's fuzzyfinder (fzf)
Home-page: https://github.com/nk412/pyfzf
Author: Nagarjuna Kumarappan
Author-email: nagarjuna.412@gmail.com
License: MIT
Platform: UNKNOWN
Classifier: Development Status :: 4 - Beta
Classifier: Environment :: Console
Classifier: Intended Audience :: Developers
Classifier: License :: OSI Approved :: MIT License
Classifier: Operating System :: OS Independent
Classifier: Programming Language :: Python
Classifier: Topic :: Terminals
License-File: LICENSE
